voicy/__init__.py
voicy/exceptions.py
voicy/types.py
voicy/clients/__init__.py
voicy/clients/google.py
voicy/clients/yandex.py
voicy/http/__init__.py
voicy/http/core.py
voicy-0.4.2.dist-info/LICENSE
voicy-0.4.2.dist-info/METADATA
voicy-0.4.2.dist-info/WHEEL
voicy-0.4.2.dist-info/top_level.txt
voicy-0.4.2.dist-info/RECORD
