Metadata-Version: 2.1
Name: voicy
Version: 0.4.2
Summary: Wrapper for free use Google cloud TTS.
Home-page: https://github.com/xcaq/voicy/
Author: Kirill Feschenko
Author-email: swipduces@yandex.com
License: GNU LGPLv3
Keywords: wrapper text-to-speech google-cloud tts stt tts-engines wrapper-library tts-api google-cloud-text-to-speech google-cloud-tts stt-engines stt-api google-cloud-speech-to-text
Platform: UNKNOWN
Classifier: License :: OSI Approved :: GNU Lesser General Public License v3 (LGPLv3)
Classifier: Programming Language :: Python
Classifier: Programming Language :: Python :: 3
Classifier: Programming Language :: Python :: 3.7
Classifier: Programming Language :: Python :: 3.8
Classifier: Programming Language :: Python :: 3.9
Classifier: Intended Audience :: Developers
Classifier: Operating System :: OS Independent
Classifier: Programming Language :: Python :: Implementation :: CPython
Classifier: Programming Language :: Python :: Implementation :: PyPy
Classifier: Topic :: Internet :: WWW/HTTP :: Dynamic Content :: CGI Tools/Libraries
Classifier: Typing :: Typed
Requires-Python: >=3.7.0
Requires-Dist: pydantic (==1.7.3)
Requires-Dist: python-rucaptcha (==3.0.1)
Requires-Dist: requests (==2.25.1)
Requires-Dist: pydub (==0.24.1)
